{
	"class" : {
		"exampleDataFlows" : "PeterUhnak 3/18/2016 13:41:17",
		"exampleEmpty" : "PeterUhnak 3/18/2016 13:41:17",
		"examplePizzaDelivery" : "PeterUhnak 3/18/2016 13:41:17",
		"exampleTravelingCard" : "PeterUhnak 3/18/2016 13:41:17",
		"menuCommandOn:" : "PeterUhnak 3/18/2016 13:41:17",
		"sampleDataFlows" : "PeterUhnak 3/18/2016 13:41:17",
		"sampleEmpty" : "PeterUhnak 3/18/2016 13:41:17",
		"samplePizzaDelivery" : "PeterUhnak 3/18/2016 13:41:17",
		"sampleTravelingCard" : "PeterUhnak 3/18/2016 13:41:17" },
	"instance" : {
		 } }
